chercher_plugin_md/__init__.py
chercher_plugin_md-0.1.7.dist-info/licenses/LICENSE
chercher_plugin_md-0.1.7.dist-info/METADATA
chercher_plugin_md-0.1.7.dist-info/WHEEL
chercher_plugin_md-0.1.7.dist-info/entry_points.txt
chercher_plugin_md-0.1.7.dist-info/top_level.txt
chercher_plugin_md-0.1.7.dist-info/RECORD
