Metadata-Version: 2.4
Name: chercher-plugin-md
Version: 0.1.7
Summary: Chercher plugin that adds support for markdown files.
Author-email: dnlzrgz <contact@dnlzrgz.com>
License-Expression: MIT
Project-URL: Homepage, https://github.com/dnlzrgz/chercher-plugin-md
Project-URL: Changelog, https://github.com/dnlzrgz/chercher-plugin-md/releases
Project-URL: Issues, https://github.com/dnlzrgz/chercher-plugin-md/issues
Project-URL: CI, https://github.com/dnlzrgz/chercher-plugin-md/actions
Requires-Python: >=3.13
License-File: LICENSE
Requires-Dist: chercher>=0.1.23
Requires-Dist: python-frontmatter>=1.1.0
Dynamic: license-file
